alibaba_cloud_ops_mcp_server/__init__.py
alibaba_cloud_ops_mcp_server/config.py
alibaba_cloud_ops_mcp_server/server.py
alibaba_cloud_ops_mcp_server/alibabacloud/__init__.py
alibaba_cloud_ops_mcp_server/alibabacloud/api_meta_client.py
alibaba_cloud_ops_mcp_server/alibabacloud/exception.py
alibaba_cloud_ops_mcp_server/alibabacloud/utils.py
alibaba_cloud_ops_mcp_server/tools/__init__.py
alibaba_cloud_ops_mcp_server/tools/api_tools.py
alibaba_cloud_ops_mcp_server/tools/cms_tools.py
alibaba_cloud_ops_mcp_server/tools/oos_tools.py
alibaba_cloud_ops_mcp_server/tools/oss_tools.py
my_alibaba_cloud_ops_mcp_server-0.8.9.dist-info/METADATA
my_alibaba_cloud_ops_mcp_server-0.8.9.dist-info/WHEEL
my_alibaba_cloud_ops_mcp_server-0.8.9.dist-info/entry_points.txt
my_alibaba_cloud_ops_mcp_server-0.8.9.dist-info/licenses/LICENSE
my_alibaba_cloud_ops_mcp_server-0.8.9.dist-info/RECORD
