Metadata-Version: 2.4
Name: my-alibaba-cloud-ops-mcp-server
Version: 0.8.9
Summary: A MCP server for Alibaba Cloud
Author-email: Zheng Dayu <dayu.zdy@alibaba-inc.com>
License-File: LICENSE
Requires-Python: >=3.10
Requires-Dist: alibabacloud-cms20190101>=3.1.4
Requires-Dist: alibabacloud-ecs20140526>=6.1.0
Requires-Dist: alibabacloud-oos20190601>=3.4.1
Requires-Dist: alibabacloud-oss-v2>=1.1.0
Requires-Dist: click>=8.1.8
Requires-Dist: mcp[cli]>=1.6.0
